{
  "entries": [
    {
      "title": "Republican Leaders Say They’ve Spoken With Mitch McConnell Since Hospitalization",
      "link": "https://www.nytimes.com/2026/07/07/us/politics/mitch-mcconnell-hospital-thune-barrasso.html",
      "published": "Tue, 07 Jul 2026 19:15:38 +0000",
      "sentiment": 0.5
    },
    {
      "title": "Bernie Sanders Calls on Graham Platner to Drop Senate Bid After Rape Allegation",
      "link": "https://www.nytimes.com/2026/07/07/us/politics/graham-platner-bernie-sanders-maine.html",
      "published": "Tue, 07 Jul 2026 18:23:46 +0000",
      "sentiment": 0.25
    },
    {
      "title": "Lawsuit Alleges Trump Administration Gave Iran Details on Asylum Seekers",
      "link": "https://www.nytimes.com/2026/07/07/us/politics/trump-lawsuit-iran-asylum.html",
      "published": "Tue, 07 Jul 2026 18:49:42 +0000",
      "sentiment": 0.13636363636363635
    },
    {
      "title": "The World Cup Stood as a Break From U.S. Politics. Then Trump Got Involved.",
      "link": "https://www.nytimes.com/2026/07/07/us/politics/trump-world-cup-fifa.html",
      "published": "Tue, 07 Jul 2026 18:29:22 +0000",
      "sentiment": 0.0
    },
    {
      "title": "Trump’s Top Air Pollution Regulator Will Resign",
      "link": "https://www.nytimes.com/2026/07/07/climate/aaron-szabo-epa-resign.html",
      "published": "Tue, 07 Jul 2026 17:43:53 +0000",
      "sentiment": 0.17222222222222222
    },
    {
      "title": "Democrats Clash Over Who Replaces Platner Even Before He Exits",
      "link": "https://www.nytimes.com/2026/07/07/us/politics/graham-platner-maine-replacements-democrats.html",
      "published": "Tue, 07 Jul 2026 19:13:34 +0000",
      "sentiment": 0.2
    },
    {
      "title": "Nation’s 250th Celebration Fireworks Sent D.C. Air Pollution Spiking",
      "link": "https://www.nytimes.com/2026/07/07/climate/washington-dc-fireworks-air-pollution.html",
      "published": "Tue, 07 Jul 2026 17:41:40 +0000",
      "sentiment": -0.6
    },
    {
      "title": "Trump Administration Guts Efforts to Prevent Gun Violence, Suppressing Reports",
      "link": "https://www.nytimes.com/2026/07/07/us/politics/trump-gun-violence-cdc-dhs-justice.html",
      "published": "Tue, 07 Jul 2026 16:03:43 +0000",
      "sentiment": 0.0
    },
    {
      "title": "Abandoned by Allies, Graham Platner Faces Pressure to End Maine Senate Campaign",
      "link": "https://www.nytimes.com/2026/07/07/us/politics/graham-platner-maine-senate.html",
      "published": "Tue, 07 Jul 2026 09:04:21 +0000",
      "sentiment": 0.06666666666666667
    },
    {
      "title": "The History at the Smithsonian That the White House Finds Unpatriotic",
      "link": "https://www.nytimes.com/2026/07/07/arts/smithsonian-trump-george-washington.html",
      "published": "Tue, 07 Jul 2026 13:35:35 +0000",
      "sentiment": 0.0
    },
    {
      "title": "After Courting Black Voters, Trump Downplays Black Unemployment",
      "link": "https://www.nytimes.com/2026/07/07/us/politics/trump-black-voters-unemployment.html",
      "published": "Tue, 07 Jul 2026 09:01:42 +0000",
      "sentiment": 0.037777777777777785
    },
    {
      "title": "Iran’s Strikes on Ships in Strait of Hormuz Test Cease-Fire and Threaten Oil Flow",
      "link": "https://www.nytimes.com/2026/07/07/world/middleeast/iran-war-oman-hormuz-tanker.html",
      "published": "Tue, 07 Jul 2026 18:56:17 +0000",
      "sentiment": 0.25
    },
    {
      "title": "In CNN Interview, Woman Details Alleged Sexual Assault by Graham Platner",
      "link": "https://www.nytimes.com/2026/07/06/us/politics/jenny-racicot-cnn-interview-graham-platner.html",
      "published": "Tue, 07 Jul 2026 00:50:45 +0000",
      "sentiment": 0.3
    },
    {
      "title": "Trump Expected to Tell Turkey He Is Ready to Restore Access to F-35 Jets",
      "link": "https://www.nytimes.com/2026/07/06/us/politics/trump-turkey-f35.html",
      "published": "Tue, 07 Jul 2026 10:01:11 +0000",
      "sentiment": 0.05
    },
    {
      "title": "Platner Faces Growing Democratic Calls to Drop Out",
      "link": "https://www.nytimes.com/2026/07/06/us/politics/platner-democrats-drop-out.html",
      "published": "Tue, 07 Jul 2026 01:07:28 +0000",
      "sentiment": 0.5
    },
    {
      "title": "Trump Tries to Take Credit for Walmart Price Cuts of Beef and Other Products",
      "link": "https://www.nytimes.com/2026/07/06/us/politics/walmart-price-cuts-beef-trump.html",
      "published": "Mon, 06 Jul 2026 22:40:55 +0000",
      "sentiment": -0.1125
    },
    {
      "title": "Who Might Replace Graham Platner if He Drops Out of the Maine Senate Race?",
      "link": "https://www.nytimes.com/2026/07/06/us/politics/who-would-replace-graham-platner-maine.html",
      "published": "Mon, 06 Jul 2026 22:30:20 +0000",
      "sentiment": 0.0
    },
    {
      "title": "What Polls Say About the Fight for the Senate",
      "link": "https://www.nytimes.com/2026/07/06/us/politics/senate-polls-platner.html",
      "published": "Mon, 06 Jul 2026 22:20:23 +0000",
      "sentiment": 0.0
    },
    {
      "title": "Inside Trump’s Ideological Fight With the Smithsonian",
      "link": "https://www.nytimes.com/2026/07/06/us/politics/trump-smithsonian-ideological-fight.html",
      "published": "Tue, 07 Jul 2026 13:33:08 +0000",
      "sentiment": 0.04999999999999999
    },
    {
      "title": "Key Health Care Panel Is Again Blocked From Meeting Under RFK Jr.",
      "link": "https://www.nytimes.com/2026/07/06/us/politics/uspstf-meeting-rfk-jr.html",
      "published": "Mon, 06 Jul 2026 21:54:58 +0000",
      "sentiment": 0.0
    },
    {
      "title": "Platner’s campaign has been dogged by controversy from the beginning.",
      "link": "https://www.nytimes.com/live/2026/07/06/us/platner-campaign-accusation/platner-campaign-controversies",
      "published": "Mon, 06 Jul 2026 21:42:29 +0000",
      "sentiment": 0.0
    },
    {
      "title": "Trump Passports Debut, Delighting Some and Dismaying Others",
      "link": "https://www.nytimes.com/2026/07/06/travel/trump-passports-traveler-reactions.html",
      "published": "Mon, 06 Jul 2026 21:05:11 +0000",
      "sentiment": 0.19999999999999998
    },
    {
      "title": "Platner’s Democratic Support Evaporates After Sexual Assault Allegation",
      "link": "https://www.nytimes.com/2026/07/06/us/politics/graham-platner-maine-assault.html",
      "published": "Tue, 07 Jul 2026 02:33:43 +0000",
      "sentiment": 0.14999999999999997
    },
    {
      "title": "McConnell Has Been Hospitalized for 3 Weeks, and Aides Won’t Say Why",
      "link": "https://www.nytimes.com/2026/07/06/us/politics/mitch-mcconell-health-hospitalization.html",
      "published": "Mon, 06 Jul 2026 23:41:43 +0000",
      "sentiment": -0.2
    }
  ]
}