{
  "entries": [
    {
      "title": "Cubans Sent to U.S. Prison at Guantánamo Are Returned to Cuba",
      "link": "https://www.nytimes.com/2026/02/10/us/politics/cubans-sent-to-us-prison-at-guantanamo-are-returned-to-cuba.html",
      "published": "Tue, 10 Feb 2026 20:22:45 +0000",
      "sentiment": 0.25
    },
    {
      "title": "Lutnick Acknowledges Traveling to Epstein’s Island",
      "link": "https://www.nytimes.com/2026/02/10/us/politics/howard-lutnick-jeffrey-epstein-island.html",
      "published": "Tue, 10 Feb 2026 20:57:36 +0000",
      "sentiment": 0.0
    },
    {
      "title": "Georgia Ballot Inquiry Originated With Election Denier in Trump White House",
      "link": "https://www.nytimes.com/2026/02/10/us/politics/fulton-county-kurt-olsen-fbi-search-2020-ballots.html",
      "published": "Tue, 10 Feb 2026 20:59:12 +0000",
      "sentiment": -0.11272727272727275
    },
    {
      "title": "Michigan Judge Rebukes Justice Department’s Effort to Obtain Voter Data",
      "link": "https://www.nytimes.com/2026/02/10/us/politics/michigan-judge-voter-data.html",
      "published": "Tue, 10 Feb 2026 20:02:38 +0000",
      "sentiment": 0.025
    },
    {
      "title": "Behind the E.P.A.’s Rush to Repeal the Endangerment Finding",
      "link": "https://www.nytimes.com/2026/02/10/climate/epa-endangerment-supreme-court.html",
      "published": "Tue, 10 Feb 2026 20:17:13 +0000",
      "sentiment": -0.2
    },
    {
      "title": "DHS Shutdown Looms as Senate Democrats Reject White House ICE Deal",
      "link": "https://www.nytimes.com/2026/02/10/us/politics/trump-immigration-crackdown-dhs-shutdown-stalemate.html",
      "published": "Tue, 10 Feb 2026 18:00:35 +0000",
      "sentiment": 0.19999999999999998
    },
    {
      "title": "Former Palm Beach Police Chief Said Trump Told Him ‘Everyone’ Knew About Epstein in 2006",
      "link": "https://www.nytimes.com/2026/02/10/us/politics/trump-epstein.html",
      "published": "Tue, 10 Feb 2026 20:53:18 +0000",
      "sentiment": 0.03409090909090909
    },
    {
      "title": "The Ties That Bound the UK’s ‘Prince of Darkness’ Peter Mandelson to Jeffrey Epstein",
      "link": "https://www.nytimes.com/2026/02/10/world/europe/ties-peter-mandelson-jeffrey-epstein.html",
      "published": "Tue, 10 Feb 2026 19:57:50 +0000",
      "sentiment": 0.06818181818181818
    },
    {
      "title": "Ahead of Jobs Report, White House Seeks to Downplay Any Slowdown",
      "link": "https://www.nytimes.com/2026/02/10/us/politics/white-house-jobs.html",
      "published": "Tue, 10 Feb 2026 17:12:19 +0000",
      "sentiment": 0.21393939393939396
    },
    {
      "title": "Republican Cash Edge Threatens to Swamp Democrats in the Midterms",
      "link": "https://www.nytimes.com/2026/02/10/us/politics/republicans-democrats-midterms-fund-raising.html",
      "published": "Tue, 10 Feb 2026 16:47:42 +0000",
      "sentiment": 0.0
    },
    {
      "title": "U.S. Hands Over Some NATO Commands to European Allies",
      "link": "https://www.nytimes.com/2026/02/10/us/politics/us-nato-commands-european-allies.html",
      "published": "Tue, 10 Feb 2026 16:20:15 +0000",
      "sentiment": 0.06142857142857143
    },
    {
      "title": "Susan Collins Runs for Re-election, in One of 2026’s Top Senate Fights",
      "link": "https://www.nytimes.com/2026/02/10/us/politics/susan-collins-maine-senate-2026.html",
      "published": "Tue, 10 Feb 2026 20:19:39 +0000",
      "sentiment": 0.125
    },
    {
      "title": "Top Immigration Officials Refuse to Discuss Minnesota Shootings at Hearing",
      "link": "https://www.nytimes.com/2026/02/10/us/politics/dhs-officials-house-minnesota.html",
      "published": "Tue, 10 Feb 2026 20:01:54 +0000",
      "sentiment": 0.6
    },
    {
      "title": "Without a Border ‘Invasion,’ Texas G.O.P. Turns to an Old Enemy, Islam",
      "link": "https://www.nytimes.com/2026/02/10/us/politics/texas-muslims-republicans.html",
      "published": "Tue, 10 Feb 2026 10:02:01 +0000",
      "sentiment": 0.05
    },
    {
      "title": "Trump Administration Claims About Shootings by Federal Agents Unravel in Court",
      "link": "https://www.nytimes.com/2026/02/10/us/politics/homeland-security-shootings.html",
      "published": "Tue, 10 Feb 2026 15:47:45 +0000",
      "sentiment": 0.09999999999999998
    },
    {
      "title": "Appeals Court Lets Trump Revoke Deportation Protections for 60,000 More Migrants",
      "link": "https://www.nytimes.com/2026/02/09/us/politics/appeals-court-lets-trump-revoke-deportation-protections-for-60000-more-migrants.html",
      "published": "Tue, 10 Feb 2026 04:10:22 +0000",
      "sentiment": 0.25
    },
    {
      "title": "U.S. Boat Strike Kills 2 in Pacific, With One Survivor",
      "link": "https://www.nytimes.com/2026/02/09/us/politics/us-boat-strike-pacific-ocean.html",
      "published": "Tue, 10 Feb 2026 02:42:46 +0000",
      "sentiment": 0.03409090909090909
    },
    {
      "title": "Trump Threatens to Block Opening of New Bridge to Canada",
      "link": "https://www.nytimes.com/2026/02/09/us/politics/trump-gordie-howe-bridge-canada.html",
      "published": "Tue, 10 Feb 2026 02:41:35 +0000",
      "sentiment": 0.02727272727272727
    },
    {
      "title": "Trump Administration Abandons Steve Bannon Conviction",
      "link": "https://www.nytimes.com/2026/02/09/us/politics/bannon-trump-contempt-case.html",
      "published": "Tue, 10 Feb 2026 02:08:48 +0000",
      "sentiment": 0.0
    },
    {
      "title": "Gabbard’s 2020 Election Claims Put Her Back in Favor With Trump",
      "link": "https://www.nytimes.com/2026/02/09/us/politics/tulsi-gabbard-2020-election.html",
      "published": "Tue, 10 Feb 2026 12:11:20 +0000",
      "sentiment": 0.012499999999999997
    },
    {
      "title": "Newly Unbound, Trump Weighs More Nuclear Arms and Underground Tests",
      "link": "https://www.nytimes.com/2026/02/09/us/politics/trump-nuclear-arms-underground-tests.html",
      "published": "Tue, 10 Feb 2026 18:30:47 +0000",
      "sentiment": 0.04415584415584416
    },
    {
      "title": "Pockets of Republican Pushback to ICE Facilities Point to MAGA Fissures",
      "link": "https://www.nytimes.com/2026/02/09/us/politics/ice-detention-centers-republicans-trump.html",
      "published": "Mon, 09 Feb 2026 23:04:12 +0000",
      "sentiment": 0.2857142857142857
    },
    {
      "title": "Trump Administration to Cut $600 Million in Health Funding From Four States",
      "link": "https://www.nytimes.com/2026/02/09/health/trump-public-health-cuts-california.html",
      "published": "Mon, 09 Feb 2026 23:06:28 +0000",
      "sentiment": -0.1
    }
  ]
}