[
  {
    "score":88,
    "pubdate":"2025-10-25-09-38-00 +0000",
    "source":"wsj",
    "title":"Trump Pitches Meeting With Kim Jong Un During Asia Tour: \u2018Put Out the Word\u2019",
    "link":"https:\/\/www.wsj.com\/world\/asia\/trump-pitches-meeting-with-kim-jong-un-during-asia-tour-ba0c55ec"
  },
  {
    "score":42,
    "pubdate":"2025-10-25-23-10-24 +0000",
    "source":"nypost",
    "title":"NYC voters run to the polls on first day of early voting \u2014 with impressive five time increase to last mayoral race",
    "link":"https:\/\/nypost.com\/2025\/10\/25\/us-news\/nyc-voters-run-to-the-polls-on-first-day-of-early-voting-with-impressive-five-time-increase-to-last-mayoral-race\/"
  },
  {
    "score":38,
    "pubdate":"2025-10-26-01-51-00 +0000",
    "source":"wsj",
    "title":"Trump Says He Will Raise Tariffs on Canada by 10% Over Ontario Ad",
    "link":"https:\/\/www.wsj.com\/politics\/policy\/trump-hikes-tariffs-on-canada-by-10-over-ontario-ad-0fc64764"
  },
  {
    "score":35,
    "pubdate":"2025-10-26-01-00-00 +0000",
    "source":"wsj",
    "title":"\u201cYou have zero zoning conditions, you\u2019re the president.\u201d How Trump cut through red tape to get his White House ballroom.",
    "link":"https:\/\/www.wsj.com\/politics\/policy\/trump-white-house-ballroom-construction-d1616a3e"
  },
  {
    "score":33,
    "pubdate":"2025-10-25-15-21-49 +0000",
    "source":"nypost",
    "title":"Chilling footage shows Russian drone hunting down Ukrainian farmers in \u2018staged safari\u2019: \u2018This is another war crime\u2019",
    "link":"https:\/\/nypost.com\/2025\/10\/25\/world-news\/chilling-footage-shows-russian-drone-hunting-down-ukrainian-farmers-in-staged-safari-this-is-another-war-crime\/"
  },
  {
    "score":31,
    "pubdate":"2025-10-26-05-21-38 +0000",
    "source":"nypost",
    "title":"Bikini-clad Brazilian influencer Melissa Said breaks silence after she\u2019s arrested, accused of being drug trafficking queen",
    "link":"https:\/\/nypost.com\/2025\/10\/26\/world-news\/brazilian-influencer-melissa-said-breaks-silence-after-shes-arrested-accused-of-being-drug-trafficking-queen\/"
  },
  {
    "score":28,
    "pubdate":"2025-10-26-03-08-19 +0000",
    "source":"nypost",
    "title":"Sister of slain NJ man blasts cop who allegedly ignored 911 call about her brother\u2019s murder\u2014 and went to pizza shop instead",
    "link":"https:\/\/nypost.com\/2025\/10\/25\/us-news\/sister-of-slain-nj-man-blasts-cop-accused-of-skipping-911-shooting-probe-for-pizza\/"
  },
  {
    "score":26,
    "pubdate":"2025-10-25-21-58-46 +0000",
    "source":"nypost",
    "title":"Louvre heist being investigated as inside job with security guard eyed in landmark robbery: report",
    "link":"https:\/\/nypost.com\/2025\/10\/25\/world-news\/louvre-heist-being-investigated-as-inside-job-with-security-guard-eyed-in-landmark-robbery-report\/"
  },
  {
    "score":26,
    "pubdate":"2025-10-25-10-25-15 +0000",
    "source":"bbc",
    "title":"Who is new deputy Labour leader Lucy Powell?",
    "link":"https:\/\/www.bbc.com\/news\/articles\/cev1d30kjdlo?at_medium=RSS&at_campaign=rss"
  },
  {
    "score":22,
    "pubdate":"2025-10-25-20-55-20 +0000",
    "source":"nypost",
    "title":"Rubio vows to return bodies of all dead hostages \u2014 as bodies of two Americans still held by terrorists",
    "link":"https:\/\/nypost.com\/2025\/10\/25\/world-news\/rubio-vows-to-return-bodies-of-all-dead-hostages-as-israeli-officials-hope-hamas-returns-two-more-on-sunday-we-will-not-rest\/"
  }
]