{
  "entries": [
    {
      "title": "Bone found by YouTuber searching for Nancy Guthrie was around 750 years old",
      "link": "https://www.washingtonpost.com/nation/2026/05/22/bone-found-by-youtuber-searching-nancy-guthrie-was-around-750-years-old/",
      "published": "Fri, 22 May 2026 10:00:01 +0000",
      "sentiment": 0.15000000000000002
    },
    {
      "title": "Trump offered White South Africans a new life. Thousands took him up on it.",
      "link": "https://www.washingtonpost.com/nation/2026/05/22/trump-offered-white-south-africans-new-life-thousands-took-him-up-it/",
      "published": "Fri, 22 May 2026 10:00:01 +0000",
      "sentiment": 0.05909090909090909
    },
    {
      "title": "Rafe Pomerance, who helped sound the alarm on climate change, dies at 79",
      "link": "https://www.washingtonpost.com/obituaries/2026/05/21/rafe-pomerance-who-helped-sound-alarm-climate-change-dies-79/",
      "published": "Thu, 21 May 2026 17:51:41 +0000",
      "sentiment": 0.325
    },
    {
      "title": "Subpoena bill would curtail secretive tool used to target government critics",
      "link": "https://www.washingtonpost.com/nation/2026/05/21/us-lawmakers-propose-bill-curtail-administrative-subpoenas/",
      "published": "Thu, 21 May 2026 10:00:01 +0000",
      "sentiment": 0.0
    },
    {
      "title": "San Diego mosque attack followed a familiar online script",
      "link": "https://www.washingtonpost.com/nation/2026/05/21/san-diego-mosque-shooting-reveals-deadly-online-blueprint-killers/",
      "published": "Thu, 21 May 2026 09:00:00 +0000",
      "sentiment": -0.016666666666666673
    }
  ]
}