{
  "entries": [
    {
      "title": "US economy grows at fastest pace in two years",
      "link": "https://www.bbc.com/news/articles/c62n9ynzrdpo?at_medium=RSS&at_campaign=rss",
      "published": "Tue, 23 Dec 2025 15:56:57 GMT",
      "sentiment": 0.16666666666666669
    },
    {
      "title": "Government waters down inheritance tax plan for farms",
      "link": "https://www.bbc.com/news/articles/c8e9n3y28g1o?at_medium=RSS&at_campaign=rss",
      "published": "Tue, 23 Dec 2025 17:29:09 GMT",
      "sentiment": -0.15555555555555556
    },
    {
      "title": "US denies visas to ex-EU commissioner and others over social media rules",
      "link": "https://www.bbc.com/news/articles/cp39kngz008o?at_medium=RSS&at_campaign=rss",
      "published": "Wed, 24 Dec 2025 00:45:28 GMT",
      "sentiment": 0.13333333333333333
    },
    {
      "title": "Rivalries and rumours: How the new order of the Murdoch dynasty is playing out",
      "link": "https://www.bbc.com/news/articles/clyd12d38jgo?at_medium=RSS&at_campaign=rss",
      "published": "Wed, 24 Dec 2025 01:25:13 GMT",
      "sentiment": 0.13636363636363635
    },
    {
      "title": "Bet365 boss pay package rises to £280m",
      "link": "https://www.bbc.com/news/articles/c1j914rj64do?at_medium=RSS&at_campaign=rss",
      "published": "Tue, 23 Dec 2025 11:39:05 GMT",
      "sentiment": 0.25
    },
    {
      "title": "The showers and baths keeping data centre tech cool",
      "link": "https://www.bbc.com/news/articles/cp8zd176516o?at_medium=RSS&at_campaign=rss",
      "published": "Tue, 23 Dec 2025 00:04:45 GMT",
      "sentiment": 0.20909090909090908
    },
    {
      "title": "TikTok removes AI weight loss ads from fake Boots account",
      "link": "https://www.bbc.com/news/articles/c997lkdjdy5o?at_medium=RSS&at_campaign=rss",
      "published": "Tue, 23 Dec 2025 09:23:51 GMT",
      "sentiment": -0.25
    },
    {
      "title": "Our son can't come home for Christmas after insulation mould took over",
      "link": "https://www.bbc.com/news/articles/cz0ne0k70dro?at_medium=RSS&at_campaign=rss",
      "published": "Tue, 23 Dec 2025 07:44:32 GMT",
      "sentiment": -0.125
    },
    {
      "title": "Who are the frontrunners for the top Fed job?",
      "link": "https://www.bbc.com/news/articles/c4g907zekllo?at_medium=RSS&at_campaign=rss",
      "published": "Tue, 23 Dec 2025 06:01:14 GMT",
      "sentiment": 0.17045454545454544
    },
    {
      "title": "Amazon blocks 1,800 job applications from suspected North Korean agents",
      "link": "https://www.bbc.com/news/articles/c3e0kw80wwzo?at_medium=RSS&at_campaign=rss",
      "published": "Tue, 23 Dec 2025 02:49:45 GMT",
      "sentiment": -0.26666666666666666
    },
    {
      "title": "US regulator approves pill form of Wegovy weight-loss drug",
      "link": "https://www.bbc.com/news/articles/ce86le5dyxyo?at_medium=RSS&at_campaign=rss",
      "published": "Tue, 23 Dec 2025 01:29:07 GMT",
      "sentiment": 0.425
    },
    {
      "title": "Post Office had deal with Fujitsu to fix Horizon errors 19 years ago",
      "link": "https://www.bbc.com/news/articles/cqlkx6n15ero?at_medium=RSS&at_campaign=rss",
      "published": "Mon, 22 Dec 2025 18:25:38 GMT",
      "sentiment": -0.4
    },
    {
      "title": "US pauses offshore wind projects over security concerns",
      "link": "https://www.bbc.com/news/articles/cd74lyr094vo?at_medium=RSS&at_campaign=rss",
      "published": "Mon, 22 Dec 2025 21:02:43 GMT",
      "sentiment": 0.225
    },
    {
      "title": "English councils warned against adopting four-day week",
      "link": "https://www.bbc.com/news/articles/cgl6j8n04eno?at_medium=RSS&at_campaign=rss",
      "published": "Tue, 23 Dec 2025 02:44:50 GMT",
      "sentiment": 0.0
    },
    {
      "title": "Call of Duty co-creator Vince Zampella dies in California car crash",
      "link": "https://www.bbc.com/news/articles/cx25rled0ylo?at_medium=RSS&at_campaign=rss",
      "published": "Tue, 23 Dec 2025 10:04:47 GMT",
      "sentiment": -0.4
    },
    {
      "title": "Lush co-founder takes pride in being a 'woke nerd'",
      "link": "https://www.bbc.com/news/articles/cjrj9529yn5o?at_medium=RSS&at_campaign=rss",
      "published": "Mon, 22 Dec 2025 12:15:13 GMT",
      "sentiment": 0.13
    },
    {
      "title": "Petrol and diesel profit margins still persistently high, says watchdog",
      "link": "https://www.bbc.com/news/articles/c2dzk4kz722o?at_medium=RSS&at_campaign=rss",
      "published": "Mon, 22 Dec 2025 14:29:52 GMT",
      "sentiment": -0.1075
    },
    {
      "title": "Gold and silver hit records as investors hunt for safety",
      "link": "https://www.bbc.com/news/articles/cd74ldr2zryo?at_medium=RSS&at_campaign=rss",
      "published": "Mon, 22 Dec 2025 14:35:14 GMT",
      "sentiment": 0.5
    },
    {
      "title": "Uber and Lyft announce plans to trial Chinese robotaxis in UK in 2026",
      "link": "https://www.bbc.com/news/articles/cy8jmx1dl9ro?at_medium=RSS&at_campaign=rss",
      "published": "Mon, 22 Dec 2025 14:08:48 GMT",
      "sentiment": 0.0
    },
    {
      "title": "Why the railways often seem to be in such chaos over Christmas",
      "link": "https://www.bbc.com/news/articles/czdg795m5epo?at_medium=RSS&at_campaign=rss",
      "published": "Mon, 22 Dec 2025 00:03:12 GMT",
      "sentiment": 0.14285714285714285
    },
    {
      "title": "Bourbon maker Jim Beam halts production at main distillery for a year",
      "link": "https://www.bbc.com/news/articles/cy5gv5z24n2o?at_medium=RSS&at_campaign=rss",
      "published": "Mon, 22 Dec 2025 03:05:17 GMT",
      "sentiment": 0.16666666666666666
    },
    {
      "title": "Rise in gift card scams as victims lose millions",
      "link": "https://www.bbc.com/news/articles/c997jy8k7rpo?at_medium=RSS&at_campaign=rss",
      "published": "Mon, 22 Dec 2025 05:55:01 GMT",
      "sentiment": 0.0
    },
    {
      "title": "Trump says US is pursuing third oil tanker linked to Venezuela",
      "link": "https://www.bbc.com/news/articles/c99722j4lkgo?at_medium=RSS&at_campaign=rss",
      "published": "Tue, 23 Dec 2025 01:29:03 GMT",
      "sentiment": 0.0
    },
    {
      "title": "Why Croatia's capital wants to hold Europe's best Christmas market",
      "link": "https://www.bbc.com/news/articles/c8dy5m56477o?at_medium=RSS&at_campaign=rss",
      "published": "Mon, 22 Dec 2025 01:05:38 GMT",
      "sentiment": 0.6
    },
    {
      "title": "Will tech trump tradition at bakers and biscuit makers?",
      "link": "https://www.bbc.com/news/articles/cly5gen0gj8o?at_medium=RSS&at_campaign=rss",
      "published": "Fri, 19 Dec 2025 00:07:27 GMT",
      "sentiment": 0.0
    },
    {
      "title": "Should more be done to tackle 'ghost jobs', vacancies that don't exist?",
      "link": "https://www.bbc.com/news/articles/clyzvpp8g3vo?at_medium=RSS&at_campaign=rss",
      "published": "Thu, 18 Dec 2025 00:00:37 GMT",
      "sentiment": 0.45
    },
    {
      "title": "Why this month's inflation figure may be good news for you",
      "link": "https://www.bbc.com/news/articles/c0r9x1xx0x7o?at_medium=RSS&at_campaign=rss",
      "published": "Wed, 17 Dec 2025 14:18:10 GMT",
      "sentiment": 0.7
    },
    {
      "title": "Meet the biggest heat pumps in the world",
      "link": "https://www.bbc.com/news/articles/c17p44w87rno?at_medium=RSS&at_campaign=rss",
      "published": "Tue, 16 Dec 2025 00:06:44 GMT",
      "sentiment": 0.39999999999999997
    },
    {
      "title": "Spain's commitment to renewable energy may be in doubt",
      "link": "https://www.bbc.com/news/articles/cn410nll79po?at_medium=RSS&at_campaign=rss",
      "published": "Mon, 15 Dec 2025 00:02:06 GMT",
      "sentiment": 0.175
    },
    {
      "title": "'It's amazing' – the wonder material very few can make",
      "link": "https://www.bbc.com/news/articles/c24l223d9n7o?at_medium=RSS&at_campaign=rss",
      "published": "Fri, 12 Dec 2025 00:03:10 GMT",
      "sentiment": 0.21333333333333337
    },
    {
      "title": "Japan is facing a dementia crisis – can technology help?",
      "link": "https://www.bbc.com/news/articles/c4g9e34yzvgo?at_medium=RSS&at_campaign=rss",
      "published": "Mon, 08 Dec 2025 00:49:01 GMT",
      "sentiment": 0.0
    },
    {
      "title": "Fish and chip shop offers 100 free Christmas meals",
      "link": "https://www.bbc.com/news/articles/cm20gql79lzo?at_medium=RSS&at_campaign=rss",
      "published": "Tue, 23 Dec 2025 12:44:59 GMT",
      "sentiment": 0.25
    },
    {
      "title": "Food bank supplier saved by 'incredible' donation",
      "link": "https://www.bbc.com/news/articles/cp84e0xgygdo?at_medium=RSS&at_campaign=rss",
      "published": "Tue, 23 Dec 2025 11:38:53 GMT",
      "sentiment": 0.9
    },
    {
      "title": "'Put wellbeing first' to avoid festive overwhelm",
      "link": "https://www.bbc.com/news/articles/c0r9dz45xg4o?at_medium=RSS&at_campaign=rss",
      "published": "Mon, 22 Dec 2025 12:44:18 GMT",
      "sentiment": 0.25
    },
    {
      "title": "Christmas busier than Mother's Day, florist says",
      "link": "https://www.bbc.com/news/articles/cly5p1k0581o?at_medium=RSS&at_campaign=rss",
      "published": "Mon, 22 Dec 2025 06:33:56 GMT",
      "sentiment": -0.25
    },
    {
      "title": "Charity welcomes living wage rise in January",
      "link": "https://www.bbc.com/news/articles/c3v12rnxe52o?at_medium=RSS&at_campaign=rss",
      "published": "Sun, 21 Dec 2025 12:01:52 GMT",
      "sentiment": 0.13636363636363635
    },
    {
      "title": "Budget 2025: What's the best and worst that could happen for Labour?",
      "link": "https://www.bbc.com/news/articles/cqlk5gd3kv9o?at_medium=RSS&at_campaign=rss",
      "published": "Sat, 29 Nov 2025 15:14:47 GMT",
      "sentiment": -0.03333333333333333
    },
    {
      "title": "Has Britain's budget watchdog become too all-powerful?",
      "link": "https://www.bbc.com/news/articles/clyx9n5p7v7o?at_medium=RSS&at_campaign=rss",
      "published": "Tue, 25 Nov 2025 00:00:03 GMT",
      "sentiment": 0.0
    },
    {
      "title": "The curious case of why Poundland is struggling during a cost-of-living crisis",
      "link": "https://www.bbc.com/news/articles/c4gkgxeeyzno?at_medium=RSS&at_campaign=rss",
      "published": "Fri, 21 Nov 2025 08:03:37 GMT",
      "sentiment": 0.028518518518518526
    },
    {
      "title": "The £5.30 orange juice that tells the story of why supermarket prices are sky high",
      "link": "https://www.bbc.com/news/articles/c397n3jl3z8o?at_medium=RSS&at_campaign=rss",
      "published": "Wed, 22 Oct 2025 06:58:17 GMT",
      "sentiment": 0.10888888888888888
    },
    {
      "title": "How Milei's 'Thatcherite' economics divided his nation - but won over Trump",
      "link": "https://www.bbc.com/news/articles/c9865l8540eo?at_medium=RSS&at_campaign=rss",
      "published": "Tue, 14 Oct 2025 12:26:40 GMT",
      "sentiment": -0.2333333333333333
    },
    {
      "title": "What does TikTok's deal mean for America's users?",
      "link": "https://www.bbc.com/news/videos/c5yje8pvg8jo?at_medium=RSS&at_campaign=rss",
      "published": "Fri, 19 Dec 2025 09:22:13 GMT",
      "sentiment": -0.3125
    },
    {
      "title": "Americast",
      "link": "https://www.bbc.co.uk/sounds/play/p0mpmfcp?at_medium=RSS&at_campaign=rss",
      "published": "Fri, 19 Dec 2025 11:42:00 GMT",
      "sentiment": 0.0
    },
    {
      "title": "Who are the winners and losers of the interest rate cut?",
      "link": "https://www.bbc.com/news/videos/c0l9ele319lo?at_medium=RSS&at_campaign=rss",
      "published": "Thu, 18 Dec 2025 14:06:55 GMT",
      "sentiment": -0.2
    },
    {
      "title": "Inflation is at its Lowest for Eight Months",
      "link": "https://www.bbc.co.uk/iplayer/episode/l0057ryc?at_medium=RSS&at_campaign=rss",
      "published": "Wed, 17 Dec 2025 13:23:20 GMT",
      "sentiment": 0.2
    },
    {
      "title": "Lower Clothing and Food Prices Help Inflation Fall",
      "link": "https://www.bbc.co.uk/iplayer/episode/l0057rxv?at_medium=RSS&at_campaign=rss",
      "published": "Wed, 17 Dec 2025 11:01:18 GMT",
      "sentiment": -0.05
    }
  ]
}