{
  "entries": [
    {
      "title": "This suburb could be the first Minnesota city to hit pause on large-scale data centers",
      "link": "https://www.startribune.com/eagan-data-center-moratorium/601581237",
      "published": "Tue, 17 Feb 2026 19:17:14 GMT",
      "sentiment": 0.21212121212121213
    },
    {
      "title": "Should Minneapolis deny liquor licenses to hotels that housed ICE agents? City Council debates it.",
      "link": "https://www.startribune.com/minneapolis-city-council-liquor-license-hotels-ice-agents/601583286",
      "published": "Tue, 17 Feb 2026 23:35:16 GMT",
      "sentiment": 0.0
    },
    {
      "title": "Slain DFL Leader Melissa Hortman is remembered for legacy of service as lawmakers reconvene",
      "link": "https://www.startribune.com/what-to-watch-as-minnesota-legislature-returns-for-2026-session/601579829",
      "published": "Tue, 17 Feb 2026 23:02:03 GMT",
      "sentiment": 0.0
    },
    {
      "title": "Snowstorm to pummel Minnesota’s Arrowhead region",
      "link": "https://www.startribune.com/winter-storm-warning-minnesota-north/601583753",
      "published": "Tue, 17 Feb 2026 19:09:07 GMT",
      "sentiment": 0.0
    },
    {
      "title": "Journalist, activist plead not guilty to federal charges tied to St. Paul church protest",
      "link": "https://www.startribune.com/independent-journalist-black-lives-matter-co-founder-plead-not-guilty-to-federal-charges-tied-to-st-paul-church-protest/601583398",
      "published": "Tue, 17 Feb 2026 21:14:32 GMT",
      "sentiment": 0.16666666666666666
    },
    {
      "title": "Company withdraws plan to expand mine into Mississippi River",
      "link": "https://www.startribune.com/mine-grey-cloud-island-mississippi-river/601583292",
      "published": "Tue, 17 Feb 2026 23:13:54 GMT",
      "sentiment": 0.025
    },
    {
      "title": "Mike Conley returns to Timberwolves after being traded twice at the deadline",
      "link": "https://www.startribune.com/minnesota-timberwolves-mike-conley-returns-anthony-edwards-allstar-break/601583795",
      "published": "Tue, 17 Feb 2026 18:50:45 GMT",
      "sentiment": 0.0
    },
    {
      "title": "Let these Minnesota Olympians be your guide",
      "link": "https://www.startribune.com/2026-winter-olympics-lindsey-vonn-jessie-diggins-paula-moltzan-advice-coaching/601558941",
      "published": "Tue, 17 Feb 2026 21:11:34 GMT",
      "sentiment": 0.0
    },
    {
      "title": "Twins All-Star pitcher Pablo López likely will miss the 2026 season because of elbow injury",
      "link": "https://www.startribune.com/pablo-lopez-injury-update-twins-spring-training-bobby-nightengale/601583098",
      "published": "Wed, 18 Feb 2026 00:27:17 GMT",
      "sentiment": 0.08333333333333333
    },
    {
      "title": "Jason Matheson’s sidekick, Alexis Thompson, dropped from MyTalk radio show",
      "link": "https://www.startribune.com/jason-mathesons-sidekick-alexis-thompson-dropped-from-mytalk-radio-show/601583755",
      "published": "Tue, 17 Feb 2026 18:35:00 GMT",
      "sentiment": -0.0625
    }
  ]
}