{
  "entries": [
    {
      "title": "Why WH chief of staff Susie Wiles says teetotaling Trump has ‘an alcoholic’s personality’",
      "link": "https://nypost.com/2025/12/16/us-news/why-chief-of-staff-susie-wiles-says-teetotaling-trump-has-alcoholics-personality/",
      "published": "Tue, 16 Dec 2025 09:41:26 -0500",
      "sentiment": 0.02727272727272727
    },
    {
      "title": "HHS probes whether billions in taxpayer money ‘used to fuel illegal and mass migration’",
      "link": "https://nypost.com/2025/12/16/us-news/hhs-probes-whether-billions-in-taxpayer-money-used-to-fuel-illegal-and-mass-migration/",
      "published": "Tue, 16 Dec 2025 09:14:54 -0500",
      "sentiment": 0.011111111111111112
    },
    {
      "title": "Nick Reiner appearing in court Tuesday over murders of Rob, Michele Reiner",
      "link": "https://nypost.com/2025/12/16/us-news/nick-reiner-in-court-tuesday-in-alleged-murders-of-rob-michele-reiner/",
      "published": "Tue, 16 Dec 2025 08:49:15 -0500",
      "sentiment": 0.0
    },
    {
      "title": "Hochul holds strong lead despite half of New Yorkers wanting a new governor",
      "link": "https://nypost.com/2025/12/16/us-news/hochul-holds-strong-lead-despite-half-of-new-yorkers-wanting-a-new-governor/",
      "published": "Tue, 16 Dec 2025 08:38:41 -0500",
      "sentiment": 0.09653679653679655
    },
    {
      "title": "Powerball jackpot climbs to $1.25B, second-largest prize, after no winning numbers Monday",
      "link": "https://nypost.com/2025/12/16/us-news/powerball-jackpot-now-1-25-billion-after-no-one-wins-monday/",
      "published": "Tue, 16 Dec 2025 08:36:55 -0500",
      "sentiment": -0.25
    },
    {
      "title": "White House chief of staff Susie Wiles: AG Pam Bondi ‘completely whiffed’ on Epstein files, JD Vance has been ‘conspiracy theorist for a decade’",
      "link": "https://nypost.com/2025/12/16/us-news/ag-pam-bondi-completely-whiffed-handling-of-epstein-files-susie-wiles/",
      "published": "Tue, 16 Dec 2025 08:33:47 -0500",
      "sentiment": 0.15
    },
    {
      "title": "Bill, Hillary Clinton deposition in Jeffrey Epstein investigation pushed back to next month",
      "link": "https://nypost.com/2025/12/16/us-news/bill-hillary-clinton-deposition-in-jeffrey-epstein-investigation-pushed-back-to-next-month/",
      "published": "Tue, 16 Dec 2025 07:41:17 -0500",
      "sentiment": 0.049999999999999996
    },
    {
      "title": "National Education Association instructs staff on ‘neopronouns,’ ‘xeopronouns’ and battling conservative ‘villains’",
      "link": "https://nypost.com/2025/12/16/us-news/national-education-association-instructs-staff-on-neopronouns-xeopronouns-and-how-to-fight-conservative-villains/",
      "published": "Tue, 16 Dec 2025 07:17:48 -0500",
      "sentiment": 0.16818181818181818
    },
    {
      "title": "Hotel room Nick Reiner fled to after allegedly murdering parents was covered in blood: report",
      "link": "https://nypost.com/2025/12/16/us-news/hotel-room-nick-reiner-fled-to-after-allegedly-murdering-rob-and-michele-reiner-was-covered-in-blood-report/",
      "published": "Tue, 16 Dec 2025 06:51:43 -0500",
      "sentiment": -0.025
    },
    {
      "title": "Ilhan Omar lashes out at ‘sick’ Republicans for investigating her alleged marriage to brother",
      "link": "https://nypost.com/2025/12/16/us-news/ilhan-omar-lashes-out-at-sick-republicans-for-investigating-her-alleged-marriage-to-brother/",
      "published": "Tue, 16 Dec 2025 06:47:06 -0500",
      "sentiment": -0.40714285714285714
    },
    {
      "title": "Donald Trump Jr., Bettina Anderson announce engagement after year of dating: ‘The love of my life’",
      "link": "https://nypost.com/2025/12/16/us-news/donald-trump-jr-bettina-anderson-announce-engagement-after-year-of-dating-the-love-of-my-life/",
      "published": "Tue, 16 Dec 2025 06:33:39 -0500",
      "sentiment": 0.052500000000000005
    },
    {
      "title": "Inside Candace Owens’ ‘sadistic and dangerous’ world monetizing baseless conspiracies",
      "link": "https://nypost.com/2025/12/16/us-news/inside-candace-owens-sadistic-and-dangerous-world/",
      "published": "Tue, 16 Dec 2025 06:00:00 -0500",
      "sentiment": -0.6
    },
    {
      "title": "Obamas planned to meet with Rob Reiner and wife the night couple was killed",
      "link": "https://nypost.com/2025/12/16/us-news/obamas-planned-to-meet-with-rob-reiner-and-wife-the-night-couple-was-killed/",
      "published": "Tue, 16 Dec 2025 05:04:26 -0500",
      "sentiment": -0.1
    },
    {
      "title": "Erika Kirk shares update after private in-person meeting with Candace Owens",
      "link": "https://nypost.com/2025/12/16/us-news/erika-kirk-shares-update-after-private-in-person-meeting-with-candace-owens/",
      "published": "Tue, 16 Dec 2025 01:27:14 -0500",
      "sentiment": 0.11666666666666665
    },
    {
      "title": "Manspreading maniac punches NYC public school teacher in the face for simply sitting on subway",
      "link": "https://nypost.com/2025/12/16/us-news/manspreading-maniac-punches-nyc-public-school-teacher-in-the-face-for-simply-sitting-on-subway/",
      "published": "Tue, 16 Dec 2025 01:17:33 -0500",
      "sentiment": -0.1111111111111111
    },
    {
      "title": "Florida chef saves regular’s life after 78-year-old stops showing up for daily meals: ‘He’s that best friend’",
      "link": "https://nypost.com/2025/12/16/us-news/florida-chef-saves-regulars-life-after-he-stops-showing-up-for-daily-meals/",
      "published": "Tue, 16 Dec 2025 00:57:33 -0500",
      "sentiment": 0.4
    },
    {
      "title": "15 injured after San Francisco cable car comes to screeching halt",
      "link": "https://nypost.com/2025/12/16/us-news/15-injured-after-san-francisco-cable-car-suddenly-halts/",
      "published": "Tue, 16 Dec 2025 00:15:58 -0500",
      "sentiment": 0.1
    },
    {
      "title": "Beloved TikTok star Tucker Genal dead by suicide at 31: ‘Don’t even know where to begin’",
      "link": "https://nypost.com/2025/12/15/us-news/beloved-tiktok-star-tucker-genal-dead-at-31-by-suicide/",
      "published": "Mon, 15 Dec 2025 23:18:01 -0500",
      "sentiment": 0.39999999999999997
    },
    {
      "title": "Dog who disappeared from California home in 2021 found tied to Michigan fence: ‘Christmas miracle’",
      "link": "https://nypost.com/2025/12/15/us-news/dog-who-disappeared-from-california-home-in-2021-found-in-michigan/",
      "published": "Mon, 15 Dec 2025 22:37:31 -0500",
      "sentiment": -0.2
    },
    {
      "title": "Trump slaps BBC with eye-watering $10B suit for alleged defamatory editing of Jan. 6 speech",
      "link": "https://nypost.com/2025/12/15/us-news/president-trump-slaps-bbc-with-eye-watering-10b-suit-for-alleged-defamatory-editing-of-jan-6-speech/",
      "published": "Mon, 15 Dec 2025 22:27:06 -0500",
      "sentiment": -0.3666666666666667
    }
  ]
}