{
  "entries": [
    {
      "title": "Madman who pulled loaded gun on Texas pastor in church claimed to be ‘a prophet called Warlock’: cops",
      "link": "https://nypost.com/2026/04/09/us-news/madman-who-pulled-loaded-gun-on-texas-pastor-in-church-claimed-to-be-a-prophet-called-warlock-cops/",
      "published": "Thu, 09 Apr 2026 12:10:46 -0400",
      "sentiment": -0.07777777777777778
    },
    {
      "title": "Spain moves to reopen Tehran embassy after Trump goes scorched earth on  NATO",
      "link": "https://nypost.com/2026/04/09/us-news/spain-moves-to-reopen-tehran-embassy-amid-trumps-criticisms-of-nato/",
      "published": "Thu, 09 Apr 2026 12:04:03 -0400",
      "sentiment": 0.0
    },
    {
      "title": "Dad of young SF woman shot dead by ex-Biden staffer blows lid on toxic relationship behind closed doors",
      "link": "https://nypost.com/2026/04/09/us-news/dad-of-young-sf-woman-shot-dead-by-ex-biden-staffer-reveals-toxic-relationship/",
      "published": "Thu, 09 Apr 2026 12:02:12 -0400",
      "sentiment": -0.15
    },
    {
      "title": "Another mysterious NASA death as ninth scientist linked to secret programs dies",
      "link": "https://nypost.com/2026/04/09/us-news/another-mysterious-nasa-death-as-ninth-scientist-linked-to-secret-programs-dies/",
      "published": "Thu, 09 Apr 2026 11:54:31 -0400",
      "sentiment": -0.2
    },
    {
      "title": "Ivanka Trump tears up about losing her mother, Jared’s battle with cancer and watching her father get shot in ‘real time’",
      "link": "https://nypost.com/2026/04/09/us-news/ivanka-trump-tears-up-about-losing-her-mother-jareds-battle-with-cancer-and-watching-her-father-get-shot-in-real-time/",
      "published": "Thu, 09 Apr 2026 11:49:58 -0400",
      "sentiment": 0.2
    },
    {
      "title": "Majority of voters say NYC on the wrong track under Zohran Mamdani: poll",
      "link": "https://nypost.com/2026/04/09/us-news/majority-of-voters-say-nyc-on-wrong-under-mamdani-poll/",
      "published": "Thu, 09 Apr 2026 11:40:11 -0400",
      "sentiment": -0.14898989898989898
    },
    {
      "title": "San Francisco coffee shop suddenly announces its yanking all Pride flags as staff revolt",
      "link": "https://nypost.com/2026/04/09/us-news/philz-coffee-removing-pride-flags-from-stores-sparks-backlash/",
      "published": "Thu, 09 Apr 2026 11:38:37 -0400",
      "sentiment": 0.16666666666666666
    },
    {
      "title": "Ex-NYPD sergeant learns his fate after facing 15 years behind bars in fatal NYC cooler throw",
      "link": "https://nypost.com/2026/04/09/us-news/ex-nypd-sergeant-learns-his-fate-after-facing-15-years-behind-bars-in-fatal-nyc-cooler-throw/",
      "published": "Thu, 09 Apr 2026 11:37:49 -0400",
      "sentiment": -0.2
    },
    {
      "title": "Wild video shows quadruple amputee cornhole pro firing gun, snorting from $1 bill months before allegedly killing friend",
      "link": "https://nypost.com/2026/04/09/us-news/wild-video-shows-quadruple-amputee-cornhole-pro-charged-with-killing-friend-firing-gun-snorting-from-1-bill/",
      "published": "Thu, 09 Apr 2026 11:37:15 -0400",
      "sentiment": -0.04255050505050506
    },
    {
      "title": "NYC parking attendant nabbed for allegedly stalking, harassing singer H.E.R. for years",
      "link": "https://nypost.com/2026/04/09/us-news/nyc-parking-attendant-nabbed-for-allegedly-stalking-h-e-r-for-years/",
      "published": "Thu, 09 Apr 2026 11:36:19 -0400",
      "sentiment": -0.06000000000000001
    },
    {
      "title": "NJ chemistry teacher, 26, charged with having sex with student in his apartment",
      "link": "https://nypost.com/2026/04/09/us-news/nj-chemistry-teacher-26-charged-with-having-sex-with-student-in-his-apartment/",
      "published": "Thu, 09 Apr 2026 10:51:33 -0400",
      "sentiment": -0.25
    },
    {
      "title": "Naked shotgun-wielding Yale alum rampages through Bay Area Tesla shop",
      "link": "https://nypost.com/2026/04/09/us-news/naked-shotgun-wielding-yale-alum-rampages-through-bay-area-tesla-shop/",
      "published": "Thu, 09 Apr 2026 10:32:47 -0400",
      "sentiment": 0.0
    },
    {
      "title": "Bloodbath at Disney as up to 1,000 jobs are set to be axed — with new CEO revealing his master plan",
      "link": "https://nypost.com/2026/04/09/us-news/disney-plans-up-to-1000-layoffs-as-new-ceo-josh-damaro-reshapes-company/",
      "published": "Thu, 09 Apr 2026 10:25:48 -0400",
      "sentiment": 0.13636363636363635
    },
    {
      "title": "Gavin Newsom’s own ‘backyard’ trashed by homeless river camps",
      "link": "https://nypost.com/2026/04/09/us-news/gavin-newsoms-own-backyard-trashed-by-homeless-river-camps/",
      "published": "Thu, 09 Apr 2026 10:00:00 -0400",
      "sentiment": 0.06666666666666665
    },
    {
      "title": "Bahamas police may have tricked Lynette Hooker’s husband into talking to them for three hours before arrest: lawyer",
      "link": "https://nypost.com/2026/04/09/us-news/bahamas-police-may-have-tricked-lynette-hookers-husband-into-talking-to-them-for-three-hours-before-arrest-lawyer/",
      "published": "Thu, 09 Apr 2026 09:59:16 -0400",
      "sentiment": -0.05
    },
    {
      "title": "New Nancy Guthrie ransom notes expose sick plot against family, ex-FBI agent claims",
      "link": "https://nypost.com/2026/04/09/us-news/nancy-guthrie-ransom-notes-exposes-sick-plot-against-family-ex-fbi-agent-claims/",
      "published": "Thu, 09 Apr 2026 09:28:10 -0400",
      "sentiment": -0.2593073593073593
    },
    {
      "title": "Burglar spent 3 nights in dorm posing as student while she stole from actual students: police",
      "link": "https://nypost.com/2026/04/09/us-news/burglar-posed-as-college-student-to-spend-3-nights-in-dorm-stealing-from-students-police/",
      "published": "Thu, 09 Apr 2026 09:20:00 -0400",
      "sentiment": -0.05
    },
    {
      "title": "How to see astronauts off California’s coast in historic Artemis II splash down Friday",
      "link": "https://nypost.com/2026/04/09/us-news/how-to-see-astronauts-off-californias-coast-in-historic-artemis-ii-splash-down-friday/",
      "published": "Thu, 09 Apr 2026 09:00:00 -0400",
      "sentiment": -0.0022222222222222253
    },
    {
      "title": "NYC ‘squatter from hell’ sends tenants fleeing from their beds as judge brushes off hearing for 2 months: ‘Unlivable’",
      "link": "https://nypost.com/2026/04/09/us-news/nyc-squatter-from-hell-sends-tenants-fleeing-from-their-beds/",
      "published": "Thu, 09 Apr 2026 08:59:10 -0400",
      "sentiment": -0.15176767676767677
    },
    {
      "title": "Sean ‘Diddy’ Combs’ lawyers to urge appeals court to overturn conviction, sentence",
      "link": "https://nypost.com/2026/04/09/us-news/sean-diddy-combs-lawyers-to-urge-appeals-court-to-overturn-conviction-sentence/",
      "published": "Thu, 09 Apr 2026 08:22:42 -0400",
      "sentiment": 0.13333333333333333
    }
  ]
}