{
  "entries": [
    {
      "title": "Two pilots dead, 2 Port Authority cops seriously injured dead as Air Canada flight, emergency vehicle collide at LaGuardia, causing airport closure: sources",
      "link": "https://nypost.com/2026/03/23/us-news/air-canada-flight-firetruck-collide-at-laguardia-reports/",
      "published": "Mon, 23 Mar 2026 00:47:20 -0400",
      "sentiment": -0.24444444444444446
    },
    {
      "title": "We’ve got The X-Factor! Simon Cowell buys California Post",
      "link": "https://nypost.com/2026/03/22/us-news/america-idol-judge-simon-cowell-buys-california-post/",
      "published": "Sun, 22 Mar 2026 23:06:34 -0400",
      "sentiment": 0.3955357142857143
    },
    {
      "title": "Suspect arrested in 22-year-old cold case murder in California",
      "link": "https://nypost.com/2026/03/22/us-news/california-man-arrested-in-22-year-old-cold-case-murder/",
      "published": "Sun, 22 Mar 2026 23:06:10 -0400",
      "sentiment": -0.23888888888888887
    },
    {
      "title": "Illegal migrant who entered under Biden charged with murdering Loyola student Sheridan Gorman, 18",
      "link": "https://nypost.com/2026/03/22/us-news/illegal-migrant-charged-with-murdering-loyola-student-sheridan-gorman/",
      "published": "Sun, 22 Mar 2026 21:54:02 -0400",
      "sentiment": -0.3
    },
    {
      "title": "TSA chaos hits California — as Gavin Newsom issues damning statement on ICE arrivals",
      "link": "https://nypost.com/2026/03/22/us-news/travel-nightmare-deepens-as-trump-taps-ice-newsom-slams-lawless-move/",
      "published": "Sun, 22 Mar 2026 21:30:48 -0400",
      "sentiment": -0.3
    },
    {
      "title": "Multiple people stabbed in downtown LA",
      "link": "https://nypost.com/2026/03/22/us-news/downtown-los-angeles-stabbing-as-five-injured/",
      "published": "Sun, 22 Mar 2026 21:30:06 -0400",
      "sentiment": 0.05
    },
    {
      "title": "Woman, 62, killed in NYC apartment fire",
      "link": "https://nypost.com/2026/03/22/us-news/woman-62-killed-in-nyc-apartment-fire/",
      "published": "Sun, 22 Mar 2026 21:23:05 -0400",
      "sentiment": -0.2
    },
    {
      "title": "Test runs begin — but LAX people-mover still years behind schedule",
      "link": "https://nypost.com/2026/03/22/us-news/test-runs-begin-but-lax-people-mover-still-years-behind-schedule/",
      "published": "Sun, 22 Mar 2026 21:08:31 -0400",
      "sentiment": -0.43333333333333335
    },
    {
      "title": "Outrage after NJ police tackled teen, 13 — who they  mistook for tattooed 22-year-old suspect",
      "link": "https://nypost.com/2026/03/22/us-news/nj-police-dogpile-on-teen-13-who-they-somehow-mistook-for-tattooed-22-year-old-suspect/",
      "published": "Sun, 22 Mar 2026 20:59:17 -0400",
      "sentiment": 0.08333333333333333
    },
    {
      "title": "Oklahoma couple allegedly used 14-year-old girl as surrogate for twins",
      "link": "https://nypost.com/2026/03/22/us-news/oklahoma-couple-allegedly-used-14-year-old-girl-as-surrogate-for-twins/",
      "published": "Sun, 22 Mar 2026 20:51:54 -0400",
      "sentiment": -0.05714285714285715
    },
    {
      "title": "Bizarre moment AOC-linked millionaire gets drag queen to endorse him for Nancy Pelosi’s seat",
      "link": "https://nypost.com/2026/03/22/us-news/bizarre-moment-aoc-linked-millionaire-gets-drag-queen-to-endorse-him-for-nancy-pelosis-seat/",
      "published": "Sun, 22 Mar 2026 20:16:49 -0400",
      "sentiment": 0.17500000000000002
    },
    {
      "title": "California entrepreneur who cozied up to the Kardashians is caught in sickening scam to line husband’s pockets",
      "link": "https://nypost.com/2026/03/22/us-news/angelique-friend-who-cozied-up-with-kim-kardashian-kylie-jenner-and-kathy-hilton-accused-of-fraud/",
      "published": "Sun, 22 Mar 2026 20:12:29 -0400",
      "sentiment": -0.43333333333333335
    },
    {
      "title": "NHL reporter Jessi Pierce shared heartbreaking photos of final outing with 3 children day before they all died in house fire",
      "link": "https://nypost.com/2026/03/22/sports/nhl-reporter-jessi-pierce-shared-photos-of-final-outing-with-3-children-day-before-they-all-died-in-house-fire/",
      "published": "Sun, 22 Mar 2026 20:06:01 -0400",
      "sentiment": 0.3
    },
    {
      "title": "Mamdani plan to drain $1B in reserves harms NYC budget, Comptroller Levine warns",
      "link": "https://nypost.com/2026/03/22/us-news/mamdanis-budget-balancing-gimmick-could-mean-next-year-is-even-worse-nyc-comptroller-levine/",
      "published": "Sun, 22 Mar 2026 19:53:28 -0400",
      "sentiment": -0.07777777777777778
    },
    {
      "title": "California military families react as soldiers deploy to Middle East amid war with Iran",
      "link": "https://nypost.com/2026/03/22/us-news/socal-military-families-react-as-soldiers-deploy-to-middle-east/",
      "published": "Sun, 22 Mar 2026 19:49:25 -0400",
      "sentiment": -0.02
    },
    {
      "title": "Santa Rosa City Schools on brink of collapse after staff got staggering pay packets: ‘Absolute havoc’",
      "link": "https://nypost.com/2026/03/22/us-news/santa-rosa-city-school-officials-making-six-figures-despite-massive-budget-issues/",
      "published": "Sun, 22 Mar 2026 19:00:05 -0400",
      "sentiment": 0.2
    },
    {
      "title": "California launches probe into price gouging as some gas stations hit over $8 per gallon",
      "link": "https://nypost.com/2026/03/22/us-news/socal-launches-probe-into-price-gouging-as-some-gas-stations-top-8-per-gallon/",
      "published": "Sun, 22 Mar 2026 18:49:04 -0400",
      "sentiment": 0.0
    },
    {
      "title": "Child predator captured at bus stop trying to flee US before major sex-assault conviction: DA",
      "link": "https://nypost.com/2026/03/22/us-news/child-predator-captured-at-bus-stop-trying-to-flee-us-da/",
      "published": "Sun, 22 Mar 2026 18:32:19 -0400",
      "sentiment": 0.09943181818181818
    },
    {
      "title": "NYC pothole reports are shattering records – over 22K – with 2026 marking first triple-digit spike in calls",
      "link": "https://nypost.com/2026/03/22/us-news/nyc-pothole-reports-are-shattering-records-over-22k-with-2026-marking-first-triple-digit-spike-in-calls/",
      "published": "Sun, 22 Mar 2026 18:14:22 -0400",
      "sentiment": 0.09545454545454546
    },
    {
      "title": "New York orders salon schools to teach curly hair treatment to curb racial discrimination",
      "link": "https://nypost.com/2026/03/22/us-news/new-york-orders-salon-schools-to-teach-curly-hair-treatment-to-curb-racial-discrimination/",
      "published": "Sun, 22 Mar 2026 18:12:58 -0400",
      "sentiment": 0.11393939393939394
    }
  ]
}