{
  "entries": [
    {
      "title": "Israel's yellow line in Gaza is moving, expanding IDF's control, visual investigation shows",
      "link": "https://www.cbc.ca/news/investigates/satellite-images-gaza-yellow-line-9.7257822?cmp=rss",
      "published": "Wed, 05 Aug 2020 18:37:11 EDT",
      "sentiment": 0.0
    },
    {
      "title": "Massive crowds move through Iran and Iraq for Ayatollah Ali Khamenei's 6-day funeral procession",
      "link": "https://www.cbc.ca/news/world/ayatollah-ali-khamenei-funeral-procession-iran-iraq-9.7262522?cmp=rss",
      "published": "Wed, 08 Jul 2026 11:56:49 EDT",
      "sentiment": 0.04285714285714285
    },
    {
      "title": "Trump says peace deal with Iran is over after sides exchange strikes",
      "link": "https://www.cbc.ca/news/world/iran-us-peace-deal-attacks-bahrain-kuwait-9.7262342?cmp=rss",
      "published": "Wed, 08 Jul 2026 05:56:17 EDT",
      "sentiment": 0.08825757575757576
    },
    {
      "title": "'Dehumanizing' racist remarks against Kylian Mbappé by senator rock World Cup",
      "link": "https://www.cbc.ca/news/world/world-cup-mbappe-racist-comments-9.7262519?cmp=rss",
      "published": "Wed, 08 Jul 2026 12:55:53 EDT",
      "sentiment": 0.04
    },
    {
      "title": "UN inquiry urges release of Gaza hospital chief held by Israel since December 2024",
      "link": "https://www.cbc.ca/news/world/united-nations-gaza-doctor-abu-safiya-israel-9.7262421?cmp=rss",
      "published": "Wed, 08 Jul 2026 09:20:07 EDT",
      "sentiment": -5.551115123125783e-18
    },
    {
      "title": "Dolly Parton's life is a musical and it's coming to Broadway",
      "link": "https://www.cbc.ca/news/entertainment/dolly-parton-musical-coming-broadway-9.7262823?cmp=rss",
      "published": "Wed, 08 Jul 2026 13:58:23 EDT",
      "sentiment": -0.05277777777777778
    },
    {
      "title": "Boarding school where Paris Hilton says she was abused has licence revoked",
      "link": "https://www.cbc.ca/news/entertainment/utah-boarding-school-paris-hilton-loses-licence-9.7262744?cmp=rss",
      "published": "Wed, 08 Jul 2026 12:27:33 EDT",
      "sentiment": -0.17676767676767677
    },
    {
      "title": "New York City highrise deemed stable after officials earlier warned it could collapse",
      "link": "https://www.cbc.ca/news/world/new-york-city-high-rise-danger-9.7261602?cmp=rss",
      "published": "Tue, 07 Jul 2026 14:52:33 EDT",
      "sentiment": 0.014545454545454539
    },
    {
      "title": "ICE fatally shoots man during enforcement operation in Houston: DHS",
      "link": "https://www.cbc.ca/news/world/ice-houston-fatal-shooting-9.7262116?cmp=rss",
      "published": "Tue, 07 Jul 2026 19:50:39 EDT",
      "sentiment": -0.05000000000000001
    },
    {
      "title": "How Trump made $2.2B US in his 1st year back in office",
      "link": "https://www.cbc.ca/radio/donald-trump-money-9.7262485?cmp=rss",
      "published": "Wed, 08 Jul 2026 10:37:50 EDT",
      "sentiment": 0.01833333333333333
    },
    {
      "title": "Trump revives argument that U.S. should control Greenland as NATO leaders gather",
      "link": "https://www.cbc.ca/news/world/trump-greenland-nato-denmark-9.7261603?cmp=rss",
      "published": "Tue, 07 Jul 2026 15:02:59 EDT",
      "sentiment": -0.15
    },
    {
      "title": "Is Ukraine running out of interceptors? | About That",
      "link": "https://www.cbc.ca/player/play/9.7261952?cmp=rss",
      "published": "Tue, 07 Jul 2026 17:45:23 EDT",
      "sentiment": -0.03111111111111111
    },
    {
      "title": "Dozens charged with murder, extortion and more in crackdown on India-based organized crime groups",
      "link": "https://www.cbc.ca/news/world/livestory/operation-hard-ball-indictments-9.7261430?cmp=rss",
      "published": "Tue, 07 Jul 2026 13:29:03 EDT",
      "sentiment": -0.1
    },
    {
      "title": "Why Prince Harry’s court loss is a 'bitter' and 'significant setback' in his media fight",
      "link": "https://www.cbc.ca/news/world/prince-harry-court-decision-9.7260975?cmp=rss",
      "published": "Tue, 07 Jul 2026 09:23:35 EDT",
      "sentiment": -0.2255952380952381
    },
    {
      "title": "U.S. says it launched strikes on Iran for 'attacking commercial shipping' in Strait of Hormuz",
      "link": "https://www.cbc.ca/news/world/strait-of-hormuz-tanker-attack-9.7261579?cmp=rss",
      "published": "Tue, 07 Jul 2026 14:37:03 EDT",
      "sentiment": -0.09999999999999999
    },
    {
      "title": "French far-right leader Marine Le Pen to run for president after appeals court shortens public-office ban",
      "link": "https://www.cbc.ca/news/world/france-court-marine-le-pen-appeal-9.7261011?cmp=rss",
      "published": "Tue, 07 Jul 2026 09:21:21 EDT",
      "sentiment": -0.09999999999999999
    },
    {
      "title": "NATO heads to Turkey hoping to avoid a Trump blow-up",
      "link": "https://www.cbc.ca/news/politics/trump-nato-summit-ankara-9.7260138?cmp=rss",
      "published": "Tue, 07 Jul 2026 04:00:00 EDT",
      "sentiment": 0.10714285714285714
    },
    {
      "title": "Ukrainian woman suspected in Monaco bombing found dead",
      "link": "https://www.cbc.ca/news/world/ukraine-monaco-suspect-berezovska-death-9.7260933?cmp=rss",
      "published": "Tue, 07 Jul 2026 07:50:37 EDT",
      "sentiment": -0.013333333333333341
    },
    {
      "title": "Explosions rock Damascus as French President Macron visits Syria",
      "link": "https://www.cbc.ca/news/world/macron-syria-damascus-explosion-9.7260905?cmp=rss",
      "published": "Tue, 07 Jul 2026 06:13:35 EDT",
      "sentiment": 0.03888888888888889
    },
    {
      "title": "Teen snags Wilt Chamberlain's L.A. Lakers jacket at Goodwill for $4. He could make $335K",
      "link": "https://www.cbc.ca/radio/asithappens/wilt-chamberlain-jacket-goodwill-9.7260381?cmp=rss",
      "published": "Tue, 07 Jul 2026 04:00:00 EDT",
      "sentiment": 0.16825396825396824
    }
  ]
}