[
  {
    "headline": "U.S. Treasury Yields Decline",
    "link": "https://www.wsj.com/finance/investing/jgbs-mixed-may-be-supported-by-marked-fall-in-japanese-equity-market-4c39934a?mod=rss_markets_main",
    "source": "wsj",
    "pubdate": "2026-07-17-05-43-00 +0000"
  },
  {
    "headline": "NFL employee injured in Park Avenue mass shooting sues NYC for $24M over failure to stop gunman",
    "link": "https://nypost.com/2026/07/17/us-news/nfl-employee-injured-in-midtown-tower-shooting-sues-nyc-for-24m/",
    "source": "nypost",
    "pubdate": "2026-07-17-05-41-01 +0000"
  },
  {
    "headline": "Dollar-Yen Tipped to Move Gradually Toward 165 by Year-End",
    "link": "https://www.wsj.com/finance/currencies/asian-currencies-consolidate-may-be-weighed-by-risk-off-sentiment-8adc295d?mod=rss_markets_main",
    "source": "wsj",
    "pubdate": "2026-07-17-05-41-00 +0000"
  },
  {
    "headline": "School bus crash kills at least 20 pupils in Uganda",
    "link": "https://www.bbc.co.uk/news/articles/c151gegwqv1o?at_medium=RSS&at_campaign=rss",
    "source": "bbc",
    "pubdate": "2026-07-17-05-36-22 +0000"
  },
  {
    "headline": "School bus crash kills at least 20 pupils in Uganda",
    "link": "https://www.bbc.co.uk/news/articles/c151gegwqv1o?at_medium=RSS&at_campaign=rss",
    "source": "bbc",
    "pubdate": "2026-07-17-05-36-22 +0000"
  },
  {
    "headline": "China hits out at British Steel nationalisation",
    "link": "https://www.bbc.co.uk/news/articles/cjd4kvxpd3do?at_medium=RSS&at_campaign=rss",
    "source": "bbc",
    "pubdate": "2026-07-17-05-35-00 +0000"
  },
  {
    "headline": "China hits out at British Steel nationalisation",
    "link": "https://www.bbc.co.uk/news/articles/cjd4kvxpd3do?at_medium=RSS&at_campaign=rss",
    "source": "bbc",
    "pubdate": "2026-07-17-05-35-00 +0000"
  },
  {
    "headline": "China hits out at British Steel nationalisation",
    "link": "https://www.bbc.co.uk/news/articles/cjd4kvxpd3do?at_medium=RSS&at_campaign=rss",
    "source": "bbc",
    "pubdate": "2026-07-17-05-35-00 +0000"
  },
  {
    "headline": "Sweden’s EQT Expects Strong Fundraising Momentum as It Posts Higher Net Profit",
    "link": "https://www.wsj.com/business/earnings/swedens-eqt-expects-strong-fundraising-momentum-as-it-posts-higher-net-profit-48174355?mod=pls_whats_news_us_business_f",
    "source": "wsj",
    "pubdate": "2026-07-17-05-33-00 +0000"
  },
  {
    "headline": "How do you split the bill with friends?",
    "link": "https://www.bbc.co.uk/news/videos/c5yzy3j39vwo?at_medium=RSS&at_campaign=rss",
    "source": "bbc",
    "pubdate": "2026-07-17-05-26-39 +0000"
  },
  {
    "headline": "How do you split the bill with friends?",
    "link": "https://www.bbc.co.uk/news/videos/c5yzy3j39vwo?at_medium=RSS&at_campaign=rss",
    "source": "bbc",
    "pubdate": "2026-07-17-05-26-39 +0000"
  },
  {
    "headline": "Delightful World Cup Stories",
    "link": "https://www.nytimes.com/2026/07/16/world/world-cup-spain-argentina-ukraine.html",
    "source": "nyt",
    "pubdate": "2026-07-17-05-25-39 +0000"
  },
  {
    "headline": "Andy Burnham poised to become Britain’s next prime minister",
    "link": "https://nypost.com/2026/07/17/world-news/manchester-mayor-andy-burnham-positioned-to-become-britains-next-prime-minister/",
    "source": "nypost",
    "pubdate": "2026-07-17-05-24-56 +0000"
  },
  {
    "headline": "Japan relaxes royal succession rules - but ban on female emperors remain",
    "link": "https://www.bbc.co.uk/news/articles/cy07rz79zg9o?at_medium=RSS&at_campaign=rss",
    "source": "bbc",
    "pubdate": "2026-07-17-05-16-34 +0000"
  },
  {
    "headline": "Olympic cyclist admits to driving despite ban after crash that killed wife",
    "link": "https://www.bbc.co.uk/news/articles/c62q3ywep1ro?at_medium=RSS&at_campaign=rss",
    "source": "bbc",
    "pubdate": "2026-07-17-05-09-14 +0000"
  },
  {
    "headline": "Florida woman allegedly stabs friend with scissors in Uber after he told her she couldn’t drink a beer during ride",
    "link": "https://nypost.com/2026/07/17/us-news/florida-woman-lynn-marie-zamora-allegedly-stabs-friend-with-scissors-in-uber-after-he-told-her-she-couldnt-drink-a-beer-during-ride/",
    "source": "nypost",
    "pubdate": "2026-07-17-05-07-52 +0000"
  },
  {
    "headline": "Trump again makes unverifiable claims of noncitizen voting",
    "link": "https://www.nytimes.com/2026/07/16/us/politics/trump-again-makes-unfounded-claims-of-noncitizen-voting.html",
    "source": "nyt",
    "pubdate": "2026-07-17-05-02-44 +0000"
  },
  {
    "headline": "Trump again makes unverifiable claims of noncitizen voting",
    "link": "https://www.nytimes.com/2026/07/16/us/politics/trump-again-makes-unfounded-claims-of-noncitizen-voting.html",
    "source": "nyt",
    "pubdate": "2026-07-17-05-02-44 +0000"
  },
  {
    "headline": "Burnham's 'Manchesterism' got him to No 10 - but will it work for the UK?",
    "link": "https://www.bbc.co.uk/news/articles/clyl3z2xld8o?at_medium=RSS&at_campaign=rss",
    "source": "bbc",
    "pubdate": "2026-07-17-05-00-08 +0000"
  },
  {
    "headline": "Burnham's 'Manchesterism' got him to No 10 - but will it work for the UK?",
    "link": "https://www.bbc.co.uk/news/articles/clyl3z2xld8o?at_medium=RSS&at_campaign=rss",
    "source": "bbc",
    "pubdate": "2026-07-17-05-00-08 +0000"
  },
  {
    "headline": "Trump Media to sell early access to key social posts",
    "link": "https://www.bbc.co.uk/news/articles/c79gw4lj89eo?at_medium=RSS&at_campaign=rss",
    "source": "bbc",
    "pubdate": "2026-07-17-04-56-12 +0000"
  },
  {
    "headline": "Trump Media to sell early access to key social posts",
    "link": "https://www.bbc.co.uk/news/articles/c79gw4lj89eo?at_medium=RSS&at_campaign=rss",
    "source": "bbc",
    "pubdate": "2026-07-17-04-56-12 +0000"
  },
  {
    "headline": "Wacko was trapped in porta-potty tank for eight hours after trying to retrieve Mountain Dew",
    "link": "https://nypost.com/2026/07/17/us-news/wacko-was-trapped-in-porta-potty-tank-for-eight-hours-after-trying-to-retrieve-mountain-dew/",
    "source": "nypost",
    "pubdate": "2026-07-17-04-54-15 +0000"
  }
]
